relab_rpi_cam_models/__init__.py
relab_rpi_cam_models/camera.py
relab_rpi_cam_models/images.py
relab_rpi_cam_models/stream.py
relab_rpi_cam_models-0.1.1.dist-info/WHEEL
relab_rpi_cam_models-0.1.1.dist-info/METADATA
relab_rpi_cam_models-0.1.1.dist-info/RECORD
