Metadata-Version: 2.4
Name: relab-rpi-cam-models
Version: 0.1.1
Summary: Shared Pydantic models for RElab Raspberry Pi Camera plugin models
Author: Simon van Lierde
Author-email: Simon van Lierde <s.n.van.lierde@cml.leidenuniv.nl>
License-Expression: AGPL-3.0-or-later
Classifier: Development Status :: 3 - Alpha
Classifier: Framework :: FastAPI
Classifier: Natural Language :: English
Classifier: Programming Language :: Python :: 3.11
Classifier: Topic :: Multimedia :: Graphics :: Capture
Classifier: Topic :: Multimedia :: Video :: Capture
Classifier: Topic :: System :: Hardware
Requires-Dist: pillow>=10.4
Requires-Dist: pydantic>=2.9
Maintainer: Simon van Lierde
Maintainer-email: Simon van Lierde <s.n.van.lierde@cml.leidenuniv.nl>
Project-URL: Homepage, https://github.com/CMLPlatform/relab-rpi-cam-plugin
Project-URL: Issues, https://github.com/CMLPlatform/relab-rpi-cam-plugin/issues
Project-URL: Repository, https://github.com/CMLPlatform/relab-rpi-cam-plugin.git
